{"type":"FeatureCollection","features":[{"type":"Feature","id":1,"geometry":{"type":"Point","coordinates":[117.38577100000009,-0.14880299999992985]},"properties":{"sumber_gas":"Mahakam Psc","mtpa":"21.64","kontraktor":"PT Badak NGL","lng_name":"Kilang LNG Bontang","operasi":"1973","konsumen":"Ekspor, Listrik, Industri","kategori":"Fasilitas Kilang dan Tangki LNG (LNG Plant and Storage)","lokasi":"Bontang (Kaltim)","status":"Eksisting","keterangan":" ","objectid_12":1}},{"type":"Feature","id":2,"geometry":{"type":"Point","coordinates":[133.13888900000006,-2.4444399999999291]},"properties":{"sumber_gas":"Tangguh Psc","mtpa":"7.6","kontraktor":"BP Berau Ltd","lng_name":"Kilang LNG Tangguh Train I & II","operasi":"2009","konsumen":"Ekspor, Listrik, Industri","kategori":"Fasilitas Tangki LNG (LNG Storage)","lokasi":"Teluk Bintuni (Papua)","status":"Eksisting","keterangan":"Train I dan II punya kapasitas produksi yang sama: 3,8 juta metrik ton LNG. Train I dioperasikan pada Juni 2009, Train II pada kuartal ke-3 tahun 2009. Pasca pengoperasian Train I, ekspor LNG sudah langsung dimulai pada Juli 2009. Hingga 2011, tak ku","objectid_12":2}}]}